htmltable/__init__.py
htmltable/htmltable.py
htmltable_cli-0.1.11.dist-info/METADATA
htmltable_cli-0.1.11.dist-info/WHEEL
htmltable_cli-0.1.11.dist-info/entry_points.txt
htmltable_cli-0.1.11.dist-info/top_level.txt
htmltable_cli-0.1.11.dist-info/RECORD
