Metadata-Version: 2.1
Name: htmltable-cli
Version: 0.1.11
Summary: A command line tool to generate html tables with embedded images, videos and audio
Home-page: https://github.com/FarisHijazi/htmltable-cli
Author: Faris Hijazi
Author-email: theefaris@gmail.com
License: UNKNOWN
Keywords: html table htmltable html-table base64 report
Platform: UNKNOWN
Requires-Python: >=3.6
Requires-Dist: filetype
Requires-Dist: tqdm
Requires-Dist: pathlib
